CHANGES.rst
CONTRIBUTORS.rst
MANIFEST.in
README.rst
bootstrap.py
buildout.cfg
setup.py
cpskin/__init__.py
cpskin.diazotheme.dreamRightPortlet.egg-info/PKG-INFO
cpskin.diazotheme.dreamRightPortlet.egg-info/SOURCES.txt
cpskin.diazotheme.dreamRightPortlet.egg-info/dependency_links.txt
cpskin.diazotheme.dreamRightPortlet.egg-info/entry_points.txt
cpskin.diazotheme.dreamRightPortlet.egg-info/namespace_packages.txt
cpskin.diazotheme.dreamRightPortlet.egg-info/not-zip-safe
cpskin.diazotheme.dreamRightPortlet.egg-info/requires.txt
cpskin.diazotheme.dreamRightPortlet.egg-info/top_level.txt
cpskin/diazotheme/__init__.py
cpskin/diazotheme/dreamRightPortlet/__init__.py
cpskin/diazotheme/dreamRightPortlet/configure.zcml
cpskin/diazotheme/dreamRightPortlet/upgradehandlers.py
cpskin/diazotheme/dreamRightPortlet/profiles/default/cssregistry.xml
cpskin/diazotheme/dreamRightPortlet/profiles/default/jsregistry.xml
cpskin/diazotheme/dreamRightPortlet/profiles/default/lessregistry.xml
cpskin/diazotheme/dreamRightPortlet/profiles/default/metadata.xml
cpskin/diazotheme/dreamRightPortlet/profiles/default/theme.xml
cpskin/diazotheme/dreamRightPortlet/profiles/uninstall/cssregistry.xml
cpskin/diazotheme/dreamRightPortlet/profiles/uninstall/jsregistry.xml
cpskin/diazotheme/dreamRightPortlet/profiles/uninstall/lessregistry.xml
cpskin/diazotheme/dreamRightPortlet/static/manifest.cfg
cpskin/diazotheme/dreamRightPortlet/static/preview.png
cpskin/diazotheme/dreamRightPortlet/static/rules.xml
cpskin/diazotheme/dreamRightPortlet/static/css/mobile-dreamRightPortlet.css
cpskin/diazotheme/dreamRightPortlet/static/css/styles.css
cpskin/diazotheme/dreamRightPortlet/static/fragments/search.pt
cpskin/diazotheme/dreamRightPortlet/static/less/mobile.less
cpskin/diazotheme/dreamRightPortlet/static/less/mobilelarge.less
cpskin/diazotheme/dreamRightPortlet/static/less/mobilemedium.less
cpskin/diazotheme/dreamRightPortlet/static/less/styles.less
cpskin/diazotheme/dreamRightPortlet/static/less/variables.less
docs/LICENSE.GPL
docs/LICENSE.rst